cpenv/__init__.py
cpenv/__main__.py
cpenv/_self_version_check.py
cpenv/api.py
cpenv/bin/subshell.sh
cpenv/cli/__init__.py
cpenv/cli/activate.py
cpenv/cli/clone.py
cpenv/cli/copy.py
cpenv/cli/core.py
cpenv/cli/create.py
cpenv/cli/edit.py
cpenv/cli/env.py
cpenv/cli/info.py
cpenv/cli/list.py
cpenv/cli/localize.py
cpenv/cli/publish.py
cpenv/cli/remove.py
cpenv/cli/repo.py
cpenv/cli/version.py
cpenv/compat.py
cpenv/environment.py
cpenv/hooks.py
cpenv/http.py
cpenv/mappings.py
cpenv/module.py
cpenv/paths.py
cpenv/reporter.py
cpenv/repos/__init__.py
cpenv/repos/base.py
cpenv/repos/filesystem.py
cpenv/repos/shotgun.py
cpenv/resolver.py
cpenv/shell.py
cpenv/vendor/__init__.py
cpenv/vendor/appdirs.py
cpenv/vendor/cachetools/__init__.py
cpenv/vendor/cachetools/abc.py
cpenv/vendor/cachetools/cache.py
cpenv/vendor/cachetools/func.py
cpenv/vendor/cachetools/keys.py
cpenv/vendor/cachetools/lfu.py
cpenv/vendor/cachetools/lru.py
cpenv/vendor/cachetools/rr.py
cpenv/vendor/cachetools/ttl.py
cpenv/vendor/cachetools.LICENSE
cpenv/vendor/certifi/__init__.py
cpenv/vendor/certifi/__main__.py
cpenv/vendor/certifi/cacert.pem
cpenv/vendor/certifi/core.py
cpenv/vendor/certifi/py.typed
cpenv/vendor/certifi.LICENSE
cpenv/vendor/fasteners/__init__.py
cpenv/vendor/fasteners/_utils.py
cpenv/vendor/fasteners/lock.py
cpenv/vendor/fasteners/process_lock.py
cpenv/vendor/fasteners/process_mechanism.py
cpenv/vendor/fasteners/pywin32/__init__.py
cpenv/vendor/fasteners/pywin32/pywintypes.py
cpenv/vendor/fasteners/pywin32/win32con.py
cpenv/vendor/fasteners/pywin32/win32file.py
cpenv/vendor/fasteners/version.py
cpenv/vendor/README.md
cpenv/vendor/shotgun_api3/__init__.py
cpenv/vendor/shotgun_api3/lib/__init__.py
cpenv/vendor/shotgun_api3/lib/certifi/__init__.py
cpenv/vendor/shotgun_api3/lib/certifi/__main__.py
cpenv/vendor/shotgun_api3/lib/certifi/cacert.pem
cpenv/vendor/shotgun_api3/lib/certifi/core.py
cpenv/vendor/shotgun_api3/lib/certifi/py.typed
cpenv/vendor/shotgun_api3/lib/httplib2/__init__.py
cpenv-0.5.37.dist-info/entry_points.txt
cpenv-0.5.37.dist-info/LICENSE
cpenv-0.5.37.dist-info/METADATA
cpenv-0.5.37.dist-info/WHEEL
cpenv-0.5.37.dist-info/RECORD
