Metadata-Version: 2.1
Name: cpenv
Version: 0.5.37
Summary: Cross-platform module and environment management.
License: MIT
Author: Dan Bradham
Author-email: danielbradham@gmail.com
Requires-Python: >=3.6.2,<4.0.0
Classifier: License :: OSI Approved :: MIT License
Classifier: Programming Language :: Python :: 3
Classifier: Programming Language :: Python :: 3.7
Classifier: Programming Language :: Python :: 3.8
Classifier: Programming Language :: Python :: 3.9
Classifier: Programming Language :: Python :: 3.10
Classifier: Programming Language :: Python :: 3.11
Requires-Dist: colorama (>=0.4.3,<0.5.0)
Requires-Dist: fasteners (>=0.18,<0.19)
Requires-Dist: psutil (>=5.7.0,<6.0.0)
Requires-Dist: tqdm (>=4.46.0,<5.0.0)
